[
  {
    "id": "jfdfdfkgjdfkdsjkjk33",
    "userId": "klfdasljfkda",
    "userDisplayName": "Sebastion Thrun",
    "userProfPicUrl": "https://crunchbase-production-res.cloudinary.com/image/upload/c_thumb,h_256,w_256,f_auto,g_faces,z_0.7,q_auto:eco/v1477032915/mxnksvsveccaqgip2sib.png",
    "textContent": "Check out my whip",
    "photoContentUrl": "http://tomaszkacmajor.pl/wp-content/uploads/2017/05/Commercial-Udacity-ATO5C4109.jpg"
  },
  {
    "id": "jfdfdfkgjdfkdsjkjk35",
    "userId": "fkjdaljfilf334",
    "userDisplayName": "Elon Musk",
    "userProfPicUrl": "https://cdn.dialogues.org/100555/images/5762298e7b2840353640e66e/tn_01wrsjo7uk_100555.jpg",
    "textContent": "Lift off!",
    "photoContentUrl": "https://fm.cnbc.com/applications/cnbc.com/resources/img/editorial/2018/02/07/104994105-RTX4RKT8.530x298.jpg?v=1518006748"
  },
  {
    "id": "jfdfdfkgjdfkdsjkjk36",
    "userId": "fljkhadlkhuresklhu432",
    "userDisplayName": "Larry Paige",
    "userProfPicUrl": "http://shyrobotics.com/wp-content/uploads/2014/05/larry-page-128x128.jpg",
    "textContent": "I love Google!"
  },
  {
    "id": "jfdfdfkgjdfkdsjkjk37",
    "userId": "HjiorehalHdiopaj283",
    "userDisplayName": "Mark Zuckerberg",
    "userProfPicUrl": "https://assets.change.org/photos/3/pz/ur/IZPZUrJczRxOpDB-128x128-noPad.jpg?1465599428",
    "textContent": "New news feed"
  },
  {
    "id": "jfdfdfkgjdfkdsjkjk38",
    "userId": "rgjklhaklghrskjngro7",
    "userDisplayName": "Jeff Bezos",
    "userProfPicUrl": "https://pbs.twimg.com/profile_images/669103856106668033/UF3cgUk4.jpg",
    "textContent": "Meet the Echo Spot",
    "photoContentUrl": "https://icdn7.digitaltrends.com/image/amazon-echo-spot-alexa-black-640x427-c.jpg"
  },
  {
    "id": "jfdfdfkgjdfkdsjkjk39",
    "userId": "fkjdaljfilf334",
    "userDisplayName": "Bill Gates",
    "userProfPicUrl": "https://i.guim.co.uk/img/static/sys-images/Media/Pix/pictures/2006/06/21/GatesBillGetty1.jpg?w=300&q=55&auto=format&usm=12&fit=max&s=16f88f1b9f4451a65018572495dc2f51",
    "textContent": "I love Microsoft!"
  },
  {
    "id": "jfdfdfkgjdfkdsjkjk40",
    "userId": "fljkhadlkhuresklhu432",
    "userDisplayName": "Larry Paige",
    "userProfPicUrl": "http://shyrobotics.com/wp-content/uploads/2014/05/larry-page-128x128.jpg",
    "textContent": "",
    "photoContentUrl": "https://c.slashgear.com/wp-content/uploads/2016/06/google-home-product-shot-796x429-796x420.jpg"
  },
  {
    "id": "jfdfdfkgjdfkdsjkjk41",
    "userId": "HjiorehalHdiopaj283",
    "userDisplayName": "Mark Zuckerberg",
    "userProfPicUrl": "https://assets.change.org/photos/3/pz/ur/IZPZUrJczRxOpDB-128x128-noPad.jpg?1465599428",
    "textContent": "",
    "photoContentUrl": "https://fm.cnbc.com/applications/cnbc.com/resources/img/editorial/2017/01/17/104222707-GettyImages-612997084.530x298.jpg?v=1492538326"
  }
]